mfrpy/BY_example_sol.py
mfrpy/__init__.py
mfrpy/derivatives.py
mfrpy/elasticity.py
mfrpy/lin_quad.py
mfrpy/lin_quad_util.py
mfrpy/uncertain_expansion.py
mfrpy/utilities.py
mfrpy-0.0.1.dist-info/LICENSE
mfrpy-0.0.1.dist-info/WHEEL
mfrpy-0.0.1.dist-info/METADATA
mfrpy-0.0.1.dist-info/RECORD
