Metadata-Version: 2.1
Name: mfrpy
Version: 0.0.1
Summary: An open sourece DSGE solver under uncertainty
Keywords: Macroeconomics,Finance,DSGE,Uncertainty,Recursive Utility
Author: MFR Uchicago
Requires-Python: >=3.7
Classifier: Development Status :: 3 - Alpha
Classifier: Programming Language :: Python :: 3
Classifier: Programming Language :: Python :: 3.5
Classifier: Operating System :: OS Independent
Classifier: Topic :: Scientific/Engineering
Requires-Dist: autograd >= 1.4
Requires-Dist: numba >= 0.55.1
Requires-Dist: numpy >= 1.21.0
Requires-Dist: scipy >= 1.7.0
Requires-Dist: seaborn >= 0.11.0
Requires-Dist: matplotlib >= 3.5.0
Requires-Dist: pandas >= 1.4.0
Project-URL: Bug Tracker, https://github.com/lphansen/RiskUncertaintyValue
Project-URL: Homepage, https://github.com/lphansen/RiskUncertaintyValue
